slack/__init__.py
slack/deprecation.py
slack/errors.py
slack/py.typed
slack/version.py
slack/rtm/__init__.py
slack/rtm/client.py
slack/signature/__init__.py
slack/signature/verifier.py
slack/web/__init__.py
slack/web/async_base_client.py
slack/web/async_client.py
slack/web/async_internal_utils.py
slack/web/async_slack_response.py
slack/web/base_client.py
slack/web/client.py
slack/web/deprecation.py
slack/web/internal_utils.py
slack/web/slack_response.py
slack/web/classes/__init__.py
slack/web/classes/actions.py
slack/web/classes/attachments.py
slack/web/classes/blocks.py
slack/web/classes/dialog_elements.py
slack/web/classes/dialogs.py
slack/web/classes/elements.py
slack/web/classes/interactions.py
slack/web/classes/messages.py
slack/web/classes/objects.py
slack/web/classes/views.py
slack/webhook/__init__.py
slack/webhook/async_client.py
slack/webhook/client.py
slack/webhook/internal_utils.py
slack/webhook/webhook_response.py
slack_sdk/__init__.py
slack_sdk/aiohttp_version_checker.py
slack_sdk/proxy_env_variable_loader.py
slack_sdk/py.typed
slack_sdk/version.py
slack_sdk/audit_logs/__init__.py
slack_sdk/audit_logs/async_client.py
slack_sdk/audit_logs/v1/__init__.py
slack_sdk/audit_logs/v1/async_client.py
slack_sdk/audit_logs/v1/client.py
slack_sdk/audit_logs/v1/internal_utils.py
slack_sdk/audit_logs/v1/logs.py
slack_sdk/audit_logs/v1/response.py
slack_sdk/errors/__init__.py
slack_sdk/http_retry/__init__.py
slack_sdk/http_retry/async_handler.py
slack_sdk/http_retry/builtin_async_handlers.py
slack_sdk/http_retry/builtin_handlers.py
slack_sdk/http_retry/builtin_interval_calculators.py
slack_sdk/http_retry/handler.py
slack_sdk/http_retry/interval_calculator.py
slack_sdk/http_retry/jitter.py
slack_sdk/http_retry/request.py
slack_sdk/http_retry/response.py
slack_sdk/http_retry/state.py
slack_sdk/models/__init__.py
slack_sdk/models/basic_objects.py
slack_sdk/models/dialoags.py
slack_sdk/models/attachments/__init__.py
slack_sdk/models/blocks/__init__.py
slack_sdk-3.33.4.dist-info/LICENSE
slack_sdk-3.33.4.dist-info/METADATA
slack_sdk-3.33.4.dist-info/WHEEL
slack_sdk-3.33.4.dist-info/top_level.txt
slack_sdk-3.33.4.dist-info/RECORD
