Metadata-Version: 2.1
Name: slack_sdk
Version: 3.33.4
Summary: The Slack API Platform SDK for Python
Home-page: https://github.com/slackapi/python-slack-sdk
Author: Slack Technologies, LLC
Author-email: opensource@slack.com
License: MIT
Project-URL: Documentation, https://slack.dev/python-slack-sdk/
Keywords: slack,slack-api,web-api,slack-rtm,websocket,chat,chatbot,chatops
Classifier: Development Status :: 5 - Production/Stable
Classifier: Intended Audience :: Developers
Classifier: Topic :: Communications :: Chat
Classifier: Topic :: System :: Networking
Classifier: Topic :: Office/Business
Classifier: License :: OSI Approved :: MIT License
Classifier: Programming Language :: Python
Classifier: Programming Language :: Python :: 3 :: Only
Classifier: Programming Language :: Python :: 3.6
Classifier: Programming Language :: Python :: 3.7
Classifier: Programming Language :: Python :: 3.8
Classifier: Programming Language :: Python :: 3.9
Classifier: Programming Language :: Python :: 3.10
Classifier: Programming Language :: Python :: 3.11
Classifier: Programming Language :: Python :: 3.12
Classifier: Programming Language :: Python :: Implementation :: CPython
Classifier: Programming Language :: Python :: Implementation :: PyPy
Requires-Python: >=3.6
License-File: LICENSE
Provides-Extra: optional
Requires-Dist: aiodns>1.0; extra == "optional"
Requires-Dist: aiohttp<4,>=3.7.3; extra == "optional"
Requires-Dist: boto3<=2; extra == "optional"
Requires-Dist: SQLAlchemy<3,>=1.4; extra == "optional"
Requires-Dist: websockets<14,>=9.1; extra == "optional"
Requires-Dist: websocket-client<2,>=1; extra == "optional"
